[
	{
		"tu":"//img01.hua.com/uploadpic/newpic/9010011.jpg_220x240.jpg",
		"money":"￥189"
	},
	{
		"tu":"//img01.hua.com/uploadpic/newpic/9010011.jpg_220x240.jpg",
		"money":"￥189"
	},
	{
		"tu":"//img01.hua.com/uploadpic/newpic/9010011.jpg_220x240.jpg",
		"money":"￥189"
	},
	{
		"tu":"//img01.hua.com/uploadpic/newpic/9010011.jpg_220x240.jpg",
		"money":"￥189"
	},
	{
		"tu":"//img01.hua.com/uploadpic/newpic/9010011.jpg_220x240.jpg",
		"money":"￥189"
	},
	{
		"tu":"//img01.hua.com/uploadpic/newpic/9010011.jpg_220x240.jpg",
		"money":"￥189"
	},
	{
		"tu":"//img01.hua.com/uploadpic/newpic/9010011.jpg_220x240.jpg",
		"money":"￥189"
	},
	{
		"tu":"//img01.hua.com/uploadpic/newpic/9010011.jpg_220x240.jpg",
		"money":"￥189"
	}
]
